validator_pizza_python/__init__.py
validator_pizza_python/client.py
validator_pizza_python/models/__init__.py
validator_pizza_python/models/email_status.py
validator_pizza_python-1.0.0.dist-info/LICENSE
validator_pizza_python-1.0.0.dist-info/METADATA
validator_pizza_python-1.0.0.dist-info/WHEEL
validator_pizza_python-1.0.0.dist-info/top_level.txt
validator_pizza_python-1.0.0.dist-info/RECORD
