Metadata-Version: 2.1
Name: validator-pizza-python
Version: 1.0.0
Summary: Validator Pizza Python is a library for validator.pizza which detects disposable email addresses.
Home-page: https://github.com/teixeirazeus/validator-pizza-python
Author: teixeirazeus
License: MIT
Project-URL: Issue tracker, https://github.com/teixeirazeus/validator-pizza-python/issues
Classifier: Development Status :: 5 - Production/Stable
Classifier: License :: OSI Approved :: MIT License
Classifier: Intended Audience :: Developers
Classifier: Natural Language :: English
Classifier: Operating System :: OS Independent
Classifier: Programming Language :: Python :: 3
Classifier: Programming Language :: Python :: 3.6
Classifier: Programming Language :: Python :: 3.7
Classifier: Programming Language :: Python :: 3.8
Classifier: Programming Language :: Python :: 3.9
Classifier: Programming Language :: Python :: 3.10
Classifier: Topic :: Internet
Classifier: Topic :: Software Development :: Libraries
Classifier: Topic :: Software Development :: Libraries :: Python Modules
Classifier: Topic :: Utilities
Requires-Python: >=3.6
License-File: LICENSE
Requires-Dist: aiohttp
Requires-Dist: requests
